AUMCdb_MEDS/__init__.py
AUMCdb_MEDS/__main__.py
AUMCdb_MEDS/commands.py
AUMCdb_MEDS/dataset.yaml
AUMCdb_MEDS/download.py
AUMCdb_MEDS/pre_MEDS.py
AUMCdb_MEDS/configs/ETL.yaml
AUMCdb_MEDS/configs/__init__.py
AUMCdb_MEDS/configs/event_configs.yaml
AUMCdb_MEDS/configs/main.yaml
AUMCdb_MEDS/configs/runner.yaml
AUMCdb_MEDS/configs/table_preprocessors.yaml
aumcdb_meds-0.0.3.dist-info/licenses/LICENSE
aumcdb_meds-0.0.3.dist-info/METADATA
aumcdb_meds-0.0.3.dist-info/WHEEL
aumcdb_meds-0.0.3.dist-info/entry_points.txt
aumcdb_meds-0.0.3.dist-info/top_level.txt
aumcdb_meds-0.0.3.dist-info/RECORD
