Metadata-Version: 2.4
Name: AUMCdb-MEDS
Version: 0.0.3
Summary: A template ETL pipeline to extract AUMCdb data into the MEDS format.
Author-email: Patrick Rockenschaub <rockenschaub.patrick@gmail.com>
Project-URL: Homepage, https://github.com/prockenschaub/AUMCdb_MEDS
Project-URL: Issues, https://github.com/prockenschaub/AUMCdb_MEDS/issues
Classifier: Programming Language :: Python :: 3
Classifier: License :: OSI Approved :: MIT License
Classifier: Operating System :: OS Independent
Requires-Python: >=3.11
License-File: LICENSE
Requires-Dist: meds-transforms<0.4
Requires-Dist: requests
Requires-Dist: beautifulsoup4
Requires-Dist: hydra-core
Provides-Extra: dev
Requires-Dist: pre-commit<4; extra == "dev"
Provides-Extra: tests
Requires-Dist: pytest; extra == "tests"
Requires-Dist: pytest-cov; extra == "tests"
Provides-Extra: local-parallelism
Requires-Dist: hydra-joblib-launcher; extra == "local-parallelism"
Provides-Extra: slurm-parallelism
Requires-Dist: hydra-submitit-launcher; extra == "slurm-parallelism"
Dynamic: license-file
